pyzome/__init__.py
pyzome/accessor.py
pyzome/basic.py
pyzome/checks.py
pyzome/constants.py
pyzome/exceptions.py
pyzome/mock_data.py
pyzome/qglogp.py
pyzome/tem.py
pyzome/zonal_waves.py
pyzome/recipes/__init__.py
pyzome/recipes/zmd.py
pyzome-2023.9.0.dist-info/AUTHORS.rst
pyzome-2023.9.0.dist-info/LICENSE
pyzome-2023.9.0.dist-info/METADATA
pyzome-2023.9.0.dist-info/WHEEL
pyzome-2023.9.0.dist-info/top_level.txt
pyzome-2023.9.0.dist-info/RECORD
