Metadata-Version: 2.1
Name: pyzome
Version: 2023.9.0
Summary: A collection of tools for computing zonal mean and other related atmospheric circulation diagnostics
Author-email: "Zachary D. Lawrence" <zachary.lawrence@colorado.edu>
License: BSD-3-Clause
Project-URL: Source Code, https://github.com/zdlawrence/pyzome
Project-URL: Bug Tracker, https://github.com/zdlawrence/pyzome/issues
Keywords: meteorology,physics
Classifier: Development Status :: 3 - Alpha
Classifier: Programming Language :: Python :: 3
Classifier: Topic :: Scientific/Engineering
Classifier: Topic :: Scientific/Engineering :: Atmospheric Science
Classifier: Intended Audience :: Science/Research
Requires-Python: >=3.8
License-File: LICENSE
License-File: AUTHORS.rst
Requires-Dist: numpy
Requires-Dist: scipy
Requires-Dist: xarray
Requires-Dist: dask
Requires-Dist: xrft
